color/__init__.py
color/linear_color_transfer.py
color/lum_transfer.py
neural_tools-0.0.4.dist-info/METADATA
neural_tools-0.0.4.dist-info/WHEEL
neural_tools-0.0.4.dist-info/entry_points.txt
neural_tools-0.0.4.dist-info/top_level.txt
neural_tools-0.0.4.dist-info/RECORD
