Metadata-Version: 2.1
Name: neural-tools
Version: 0.0.4
Summary: Luminance and histogram matching tools
Home-page: https://github.com/ProGamerGov/Neural-Tools
Author: ProGamerGov
License: UNKNOWN
Keywords: histogram matching histogram-matching luminance transfer luminance-transfer linear-color-transfer linear color colour
Platform: UNKNOWN
Classifier: Development Status :: 5 - Production/Stable
Classifier: Intended Audience :: Science/Research
Classifier: Intended Audience :: End Users/Desktop
Classifier: Topic :: Artistic Software
Classifier: Programming Language :: Python :: 2
Classifier: Programming Language :: Python :: 3
Classifier: Operating System :: OS Independent
Requires-Dist: numpy
Requires-Dist: scipy
Requires-Dist: imageio
Requires-Dist: pillow
Requires-Dist: scikit-image
